pykell/__init__.py
pykell/arrays/__init__.py
pykell/arrays/array.py
pykell/functions/__init__.py
pykell/functions/function.py
pykell/functors/functor.py
pykell/monads/abstract.py
pykell/monads/helpers.py
pykell/monads/list.py
pykell/monads/maybe.py
pykell/typing/__init__.py
pykell/typing/containers.py
pykell/typing/types.py
pykell-0.0.2.dist-info/METADATA
pykell-0.0.2.dist-info/WHEEL
pykell-0.0.2.dist-info/licenses/LICENSE
pykell-0.0.2.dist-info/RECORD
